<?xml version="1.0" encoding="UTF-8"?>
<GenRun Id="impl_1" LaunchPart="xc7a35tcpg236-1" LaunchTime="1481295144">
  <File Type="WBT-USG" Name="usage_statistics_webtalk.html"/>
  <File Type="RDI-RDI" Name="Device_Wrapper.vdi"/>
  <File Type="BG-DRC" Name="Device_Wrapper.drc"/>
  <File Type="BG-BGN" Name="Device_Wrapper.bgn"/>
  <File Type="BITSTR-SYSDEF" Name="Device_Wrapper.sysdef"/>
  <File Type="BITSTR-MMI" Name="Device_Wrapper.mmi"/>
  <File Type="BITSTR-BMM" Name="Device_Wrapper_bd.bmm"/>
  <File Type="BITSTR-NKY" Name="Device_Wrapper.nky"/>
  <File Type="BITSTR-RBT" Name="Device_Wrapper.rbt"/>
  <File Type="BITSTR-MSK" Name="Device_Wrapper.msk"/>
  <File Type="BG-BIN" Name="Device_Wrapper.bin"/>
  <File Type="BG-BIT" Name="Device_Wrapper.bit"/>
  <File Type="POSTROUTE-PHYSOPT-TIMING-RPX" Name="Device_Wrapper_timing_summary_postroute_physopted.rpx"/>
  <File Type="POSTROUTE-PHYSOPT-TIMING-PB" Name="Device_Wrapper_timing_summary_postroute_physopted.pb"/>
  <File Type="POSTROUTE-PHYSOPT-TIMING" Name="Device_Wrapper_timing_summary_postroute_physopted.rpt"/>
  <File Type="POSTROUTE-PHYSOPT-BLACKBOX-DCP" Name="Device_Wrapper_postroute_physopt_bb.dcp"/>
  <File Type="ROUTE-CLK" Name="Device_Wrapper_clock_utilization_routed.rpt"/>
  <File Type="ROUTE-SIMILARITY" Name="Device_Wrapper_incremental_reuse_routed.rpt"/>
  <File Type="ROUTE-TIMING-RPX" Name="Device_Wrapper_timing_summary_routed.rpx"/>
  <File Type="ROUTE-TIMING-PB" Name="Device_Wrapper_timing_summary_routed.pb"/>
  <File Type="ROUTE-TIMINGSUMMARY" Name="Device_Wrapper_timing_summary_routed.rpt"/>
  <File Type="ROUTE-STATUS-PB" Name="Device_Wrapper_route_status.pb"/>
  <File Type="ROUTE-STATUS" Name="Device_Wrapper_route_status.rpt"/>
  <File Type="ROUTE-PWR-RPX" Name="Device_Wrapper_power_routed.rpx"/>
  <File Type="ROUTE-PWR-SUM" Name="Device_Wrapper_power_summary_routed.pb"/>
  <File Type="ROUTE-PWR" Name="Device_Wrapper_power_routed.rpt"/>
  <File Type="ROUTE-METHODOLOGY-DRC-PB" Name="Device_Wrapper_methodology_drc_routed.pb"/>
  <File Type="ROUTE-METHODOLOGY-DRC" Name="Device_Wrapper_methodology_drc_routed.rpt"/>
  <File Type="ROUTE-DRC-PB" Name="Device_Wrapper_drc_routed.pb"/>
  <File Type="ROUTE-DRC" Name="Device_Wrapper_drc_routed.rpt"/>
  <File Type="ROUTE-BLACKBOX-DCP" Name="Device_Wrapper_routed_bb.dcp"/>
  <File Type="ROUTE-DCP" Name="Device_Wrapper_routed.dcp"/>
  <File Type="PHYSOPT-TIMING" Name="Device_Wrapper_timing_summary_physopted.rpt"/>
  <File Type="PHYSOPT-DRC" Name="Device_Wrapper_drc_physopted.rpt"/>
  <File Type="PHYSOPT-DCP" Name="Device_Wrapper_physopt.dcp"/>
  <File Type="POSTPLACE-PWROPT-TIMING" Name="Device_Wrapper_timing_summary_postplace_pwropted.rpt"/>
  <File Type="POSTPLACE-PWROPT-DCP" Name="Device_Wrapper_postplace_pwropt.dcp"/>
  <File Type="PLACE-TIMING" Name="Device_Wrapper_timing_summary_placed.rpt"/>
  <File Type="PLACE-PRE-SIMILARITY" Name="Device_Wrapper_incremental_reuse_pre_placed.rpt"/>
  <File Type="PLACE-SIMILARITY" Name="Device_Wrapper_incremental_reuse_placed.rpt"/>
  <File Type="PLACE-CTRL" Name="Device_Wrapper_control_sets_placed.rpt"/>
  <File Type="PLACE-UTIL-PB" Name="Device_Wrapper_utilization_placed.pb"/>
  <File Type="PLACE-UTIL" Name="Device_Wrapper_utilization_placed.rpt"/>
  <File Type="PLACE-CLK" Name="Device_Wrapper_clock_utilization_placed.rpt"/>
  <File Type="PLACE-IO" Name="Device_Wrapper_io_placed.rpt"/>
  <File Type="PLACE-DCP" Name="Device_Wrapper_placed.dcp"/>
  <File Type="PWROPT-TIMING" Name="Device_Wrapper_timing_summary_pwropted.rpt"/>
  <File Type="PWROPT-DRC" Name="Device_Wrapper_drc_pwropted.rpt"/>
  <File Type="PWROPT-DCP" Name="Device_Wrapper_pwropt.dcp"/>
  <File Type="OPT-TIMING" Name="Device_Wrapper_timing_summary_opted.rpt"/>
  <File Type="OPT-HWDEF" Name="Device_Wrapper.hwdef"/>
  <File Type="OPT-METHODOLOGY-DRC" Name="Device_Wrapper_methodology_drc_opted.rpt"/>
  <File Type="OPT-DRC" Name="Device_Wrapper_drc_opted.rpt"/>
  <File Type="OPT-DCP" Name="Device_Wrapper_opt.dcp"/>
  <File Type="INIT-TIMING" Name="Device_Wrapper_timing_summary_init.rpt"/>
  <File Type="POSTROUTE-PHYSOPT-DCP" Name="Device_Wrapper_postroute_physopt.dcp"/>
  <File Type="PA-TCL" Name="Device_Wrapper.tcl"/>
  <FileSet Name="sources" Type="DesignSrcs" RelSrcDir="$PSRCDIR/sources_1">
    <Filter Type="Srcs"/>
    <File Path="$PPRDIR/../VHDL_FILES/Word_Key.vhd">
      <FileInfo>
        <Attr Name="UsedIn" Val="synthesis"/>
        <Attr Name="UsedIn" Val="simulation"/>
      </FileInfo>
    </File>
    <File Path="$PPRDIR/../VHDL_FILES/Buzzer.vhd">
      <FileInfo>
        <Attr Name="UsedIn" Val="synthesis"/>
        <Attr Name="UsedIn" Val="simulation"/>
      </FileInfo>
    </File>
    <File Path="$PPRDIR/../VHDL_FILES/Display_Word.vhd">
      <FileInfo>
        <Attr Name="UsedIn" Val="synthesis"/>
        <Attr Name="UsedIn" Val="simulation"/>
      </FileInfo>
    </File>
    <File Path="$PPRDIR/../VHDL_FILES/Timer.vhd">
      <FileInfo>
        <Attr Name="UsedIn" Val="synthesis"/>
        <Attr Name="UsedIn" Val="simulation"/>
      </FileInfo>
    </File>
    <File Path="$PPRDIR/../VHDL_FILES/Pattern_Gen.vhd">
      <FileInfo>
        <Attr Name="UsedIn" Val="synthesis"/>
        <Attr Name="UsedIn" Val="simulation"/>
      </FileInfo>
    </File>
    <File Path="$PPRDIR/../VHDL_FILES/Comparator.vhd">
      <FileInfo>
        <Attr Name="UsedIn" Val="synthesis"/>
        <Attr Name="UsedIn" Val="simulation"/>
      </FileInfo>
    </File>
    <File Path="$PPRDIR/../VHDL_FILES/Trap.vhd">
      <FileInfo>
        <Attr Name="UsedIn" Val="synthesis"/>
        <Attr Name="UsedIn" Val="simulation"/>
      </FileInfo>
    </File>
    <File Path="$PPRDIR/../VHDL_FILES/Binary_to_BCD.vhd">
      <FileInfo>
        <Attr Name="UsedIn" Val="synthesis"/>
        <Attr Name="UsedIn" Val="simulation"/>
      </FileInfo>
    </File>
    <File Path="$PPRDIR/../VHDL_FILES/Display_Key.vhd">
      <FileInfo>
        <Attr Name="UsedIn" Val="synthesis"/>
        <Attr Name="UsedIn" Val="simulation"/>
      </FileInfo>
    </File>
    <File Path="$PPRDIR/../VHDL_FILES/SSEG_Select.vhd">
      <FileInfo>
        <Attr Name="UsedIn" Val="synthesis"/>
        <Attr Name="UsedIn" Val="simulation"/>
      </FileInfo>
    </File>
    <File Path="$PPRDIR/../VHDL_FILES/End_Driver.vhd">
      <FileInfo>
        <Attr Name="UsedIn" Val="synthesis"/>
        <Attr Name="UsedIn" Val="simulation"/>
      </FileInfo>
    </File>
    <File Path="$PPRDIR/../VHDL_FILES/Init_Driver.vhd">
      <FileInfo>
        <Attr Name="UsedIn" Val="synthesis"/>
        <Attr Name="UsedIn" Val="simulation"/>
      </FileInfo>
    </File>
    <File Path="$PPRDIR/../VHDL_FILES/State_Controller.vhd">
      <FileInfo>
        <Attr Name="UsedIn" Val="synthesis"/>
        <Attr Name="UsedIn" Val="simulation"/>
      </FileInfo>
    </File>
    <File Path="$PPRDIR/../VHDL_FILES/Difficulty_Driver.vhd">
      <FileInfo>
        <Attr Name="UsedIn" Val="synthesis"/>
        <Attr Name="UsedIn" Val="simulation"/>
      </FileInfo>
    </File>
    <File Path="$PPRDIR/../VHDL_FILES/Button.vhd">
      <FileInfo>
        <Attr Name="UsedIn" Val="synthesis"/>
        <Attr Name="UsedIn" Val="simulation"/>
      </FileInfo>
    </File>
    <File Path="$PPRDIR/../VHDL_FILES/Game_Module.vhd">
      <FileInfo>
        <Attr Name="UsedIn" Val="synthesis"/>
        <Attr Name="UsedIn" Val="simulation"/>
      </FileInfo>
    </File>
    <File Path="$PPRDIR/../VHDL_FILES/Device_Wrapper.vhd">
      <FileInfo>
        <Attr Name="UsedIn" Val="synthesis"/>
        <Attr Name="UsedIn" Val="simulation"/>
      </FileInfo>
    </File>
    <File Path="$PSRCDIR/sources_1/new/End_Driver_Sim.vhd">
      <FileInfo>
        <Attr Name="UserDisabled" Val="1"/>
        <Attr Name="UsedIn" Val="synthesis"/>
        <Attr Name="UsedIn" Val="simulation"/>
      </FileInfo>
    </File>
    <Config>
      <Option Name="DesignMode" Val="RTL"/>
      <Option Name="TopModule" Val="Device_Wrapper"/>
      <Option Name="TopAutoSet" Val="TRUE"/>
    </Config>
  </FileSet>
  <FileSet Name="constrs_in" Type="Constrs" RelSrcDir="$PSRCDIR/constrs_1">
    <Filter Type="Constrs"/>
    <File Path="$PPRDIR/../VHDL_FILES/Game_Test_Const.xdc">
      <FileInfo>
        <Attr Name="UsedIn" Val="synthesis"/>
        <Attr Name="UsedIn" Val="implementation"/>
      </FileInfo>
    </File>
    <Config>
      <Option Name="TargetConstrsFile" Val="$PPRDIR/../VHDL_FILES/Game_Test_Const.xdc"/>
      <Option Name="ConstrsType" Val="XDC"/>
    </Config>
  </FileSet>
  <Strategy Version="1" Minor="2">
    <StratHandle Name="Vivado Implementation Defaults" Flow="Vivado Implementation 2016"/>
    <Step Id="init_design"/>
    <Step Id="opt_design"/>
    <Step Id="power_opt_design"/>
    <Step Id="place_design"/>
    <Step Id="post_place_power_opt_design"/>
    <Step Id="phys_opt_design"/>
    <Step Id="route_design"/>
    <Step Id="post_route_phys_opt_design"/>
    <Step Id="write_bitstream"/>
  </Strategy>
</GenRun>
